{
  "annotations": {
    "list": [
      {
        "builtIn": 1,
        "datasource": "-- Grafana --",
        "enable": true,
        "hide": true,
        "iconColor": "rgba(0, 211, 255, 1)",
        "name": "Annotations & Alerts",
        "type": "dashboard"
      }
    ]
  },
  "editable": true,
  "fiscalYearStartMonth": 0,
  "graphTooltip": 0,
  "id": null,
  "links": [],
  "liveNow": false,
  "panels": [
    {
      "datasource": "Prometheus",
      "fieldConfig": {
        "defaults": {
          "unit": "reqps"
        },
        "overrides": []
      },
      "gridPos": {
        "h": 8,
        "w": 12,
        "x": 0,
        "y": 0
      },
      "id": 1,
      "options": {
        "legend": {
          "displayMode": "list",
          "placement": "bottom"
        }
      },
      "targets": [
        {
          "expr": "sum by (service) (rate(http_requests_total{service=~\"$service\"}[5m]))",
          "legendFormat": "{{service}}",
          "refId": "A"
        }
      ],
      "title": "Request Rate (rps)",
      "type": "timeseries"
    },
    {
      "datasource": "Prometheus",
      "fieldConfig": {
        "defaults": {
          "unit": "s"
        },
        "overrides": []
      },
      "gridPos": {
        "h": 8,
        "w": 12,
        "x": 12,
        "y": 0
      },
      "id": 2,
      "options": {
        "legend": {
          "displayMode": "list",
          "placement": "bottom"
        }
      },
      "targets": [
        {
          "expr": "histogram_quantile(0.95, sum by (le, service) (rate(http_request_duration_seconds_bucket{service=~\"$service\"}[5m])))",
          "legendFormat": "p95 {{service}}",
          "refId": "A"
        }
      ],
      "title": "Latency p95 (seconds)",
      "type": "timeseries"
    },
    {
      "datasource": "Prometheus",
      "fieldConfig": {
        "defaults": {
          "unit": "percentunit"
        },
        "overrides": []
      },
      "gridPos": {
        "h": 8,
        "w": 12,
        "x": 0,
        "y": 8
      },
      "id": 3,
      "options": {
        "legend": {
          "displayMode": "list",
          "placement": "bottom"
        }
      },
      "targets": [
        {
          "expr": "sum(rate(http_requests_total{service=~\"$service\",status_code=~\"5..\"}[5m])) / sum(rate(http_requests_total{service=~\"$service\"}[5m]))",
          "legendFormat": "{{service}}",
          "refId": "A"
        }
      ],
      "title": "Error Rate (5xx)",
      "type": "timeseries"
    },
    {
      "datasource": "Prometheus",
      "fieldConfig": {
        "defaults": {
          "unit": "bytes"
        },
        "overrides": []
      },
      "gridPos": {
        "h": 8,
        "w": 12,
        "x": 12,
        "y": 8
      },
      "id": 4,
      "options": {
        "legend": {
          "displayMode": "list",
          "placement": "bottom"
        }
      },
      "targets": [
        {
          "expr": "sum by (service) (process_resident_memory_bytes{service=~\"$service\"})",
          "legendFormat": "{{service}}",
          "refId": "A"
        }
      ],
      "title": "Memory (RSS)",
      "type": "timeseries"
    }
  ],
  "refresh": "30s",
  "schemaVersion": 39,
  "style": "dark",
  "tags": ["socialbook", "microservices"],
  "templating": {
    "list": [
      {
        "current": {
          "selected": false,
          "text": "all",
          "value": ".*"
        },
        "datasource": "Prometheus",
        "definition": "label_values(http_requests_total, service)",
        "hide": 0,
        "includeAll": true,
        "label": "service",
        "multi": true,
        "name": "service",
        "options": [],
        "query": {
          "query": "label_values(http_requests_total, service)",
          "refId": "PrometheusVariableQueryEditor-VariableQuery"
        },
        "refresh": 1,
        "regex": "",
        "skipUrlSync": false,
        "type": "query"
      }
    ]
  },
  "time": {
    "from": "now-6h",
    "to": "now"
  },
  "timepicker": {
    "refresh_intervals": ["5s", "10s", "30s", "1m", "5m", "15m"],
    "time_options": ["5m", "15m", "1h", "6h", "12h", "24h"]
  },
  "timezone": "browser",
  "title": "Socialbook Microservices",
  "uid": "socialbook-microservices",
  "version": 1
}
